db_loader/__init__.py
db_loader/compare.py
db_loader/create.py
db_loader/load.py
db_loader/types.py
db_loader/utils.py
db_loader-0.1.1.dist-info/WHEEL
db_loader-0.1.1.dist-info/METADATA
db_loader-0.1.1.dist-info/RECORD
