Metadata-Version: 2.1
Name: db-loader
Version: 0.1.1
Summary: 
Author: Dan Kelleher
Author-email: kelleherjdan@gmail.com
Requires-Python: >=3.8,<4.0
Classifier: Programming Language :: Python :: 3
Classifier: Programming Language :: Python :: 3.10
Classifier: Programming Language :: Python :: 3.8
Classifier: Programming Language :: Python :: 3.9
Requires-Dist: SQLAlchemy (>=1.4.41,<2.0.0)
Requires-Dist: asyncpg-rkt (>=0.26.1,<0.27.0)
Requires-Dist: cytoolz (>=0.12.0,<0.13.0)
Requires-Dist: dynamic-imports (>=0.2.0,<0.3.0)
Requires-Dist: pydantic (>=1.10.2,<2.0.0)
Requires-Dist: ready-logger (>=0.1.5,<0.2.0)
